odoo/addons/ddmrp_packaging/README.rst
odoo/addons/ddmrp_packaging/__init__.py
odoo/addons/ddmrp_packaging/__manifest__.py
odoo/addons/ddmrp_packaging/i18n/ddmrp_packaging.pot
odoo/addons/ddmrp_packaging/models/__init__.py
odoo/addons/ddmrp_packaging/models/stock_buffer.py
odoo/addons/ddmrp_packaging/readme/CONTRIBUTORS.rst
odoo/addons/ddmrp_packaging/readme/DESCRIPTION.rst
odoo/addons/ddmrp_packaging/readme/HISTORY.rst
odoo/addons/ddmrp_packaging/readme/INSTALL.rst
odoo/addons/ddmrp_packaging/static/description/icon.png
odoo/addons/ddmrp_packaging/static/description/index.html
odoo/addons/ddmrp_packaging/views/stock_buffer_view.xml
odoo/addons/ddmrp_packaging/wizards/__init__.py
odoo/addons/ddmrp_packaging/wizards/make_procurement_buffer.py
odoo/addons/ddmrp_packaging/wizards/make_procurement_buffer_view.xml
odoo14_addon_ddmrp_packaging-14.0.1.1.0.dist-info/METADATA
odoo14_addon_ddmrp_packaging-14.0.1.1.0.dist-info/WHEEL
odoo14_addon_ddmrp_packaging-14.0.1.1.0.dist-info/top_level.txt
odoo14_addon_ddmrp_packaging-14.0.1.1.0.dist-info/RECORD
